Zero_ILumi_Calculadora_Package/Principal.py
Zero_ILumi_Calculadora_Package/__init__.py
Zero_ILumi_Calculadora_Package/Calculadora/__init__.py
Zero_ILumi_Calculadora_Package/Calculadora/Arithmetic_Operations/__init__.py
Zero_ILumi_Calculadora_Package/Calculadora/Arithmetic_Operations/divisao.py
Zero_ILumi_Calculadora_Package/Calculadora/Arithmetic_Operations/multiplicacao.py
Zero_ILumi_Calculadora_Package/Calculadora/Arithmetic_Operations/resto_divisao.py
Zero_ILumi_Calculadora_Package/Calculadora/Arithmetic_Operations/soma.py
Zero_ILumi_Calculadora_Package/Calculadora/Arithmetic_Operations/subtracao.py
Zero_ILumi_Calculadora_Package/Calculadora/Calculadora_Completa/Calcular.py
Zero_ILumi_Calculadora_Package/Calculadora/Calculadora_Completa/__init__.py
Zero_ILumi_Calculadora_Package-0.0.2.dist-info/METADATA
Zero_ILumi_Calculadora_Package-0.0.2.dist-info/WHEEL
Zero_ILumi_Calculadora_Package-0.0.2.dist-info/top_level.txt
Zero_ILumi_Calculadora_Package-0.0.2.dist-info/RECORD
