Metadata-Version: 2.1
Name: Zero-ILumi-Calculadora-Package
Version: 0.0.2
Summary: Uma Calculadora Desenvolvida por Zero_ILumi
Home-page: https://github.com/ZeroILumi/Projetos_de_Teste_ver_0.0.1/tree/master/Testes_Complexos/Pacotes%20Python/Zero_ILumi_Pacote_Teste
Author: Zero ILumi
Author-email: zeroilumi666@gmail.com
License: UNKNOWN
Platform: UNKNOWN
Requires-Python: >=3.8
Requires-Dist: django
